tls_session/__init__.py
tls_session/http2_bridge.so
tls_session/session.py
tls_sessions-1.1.2.dist-info/METADATA
tls_sessions-1.1.2.dist-info/WHEEL
tls_sessions-1.1.2.dist-info/top_level.txt
tls_sessions-1.1.2.dist-info/RECORD
